bcdamenu/LICENSE.txt
bcdamenu/__init__.py
bcdamenu/_version.py
bcdamenu/about.py
bcdamenu/about.ui
bcdamenu/bcdamenu.ini
bcdamenu/config_file_parser.py
bcdamenu/launcher.py
BcdaMenu-2019.5.0.dist-info/METADATA
BcdaMenu-2019.5.0.dist-info/WHEEL
BcdaMenu-2019.5.0.dist-info/entry_points.txt
BcdaMenu-2019.5.0.dist-info/top_level.txt
BcdaMenu-2019.5.0.dist-info/RECORD
