Metadata-Version: 2.1
Name: BcdaMenu
Version: 2019.5.0
Summary: A GUI menu button to start common software.
Home-page: http://BcdaMenu.readthedocs.io
Author: Pete Jemian
Author-email: jemian@anl.gov
License: (c) 2009-2019, UChicago Argonne, LLC
Keywords: APS,BCDA,PyQt4,PyQt5
Platform: any
Classifier: Development Status :: 4 - Beta
Classifier: Environment :: Console
Classifier: Intended Audience :: Science/Research
Classifier: License :: Free To Use But Restricted
Classifier: Operating System :: OS Independent
Classifier: Programming Language :: Python
Classifier: Programming Language :: Python :: 2
Classifier: Programming Language :: Python :: 2.7
Classifier: Programming Language :: Python :: 3
Classifier: Programming Language :: Python :: 3.5
Classifier: Programming Language :: Python :: 3.6
Classifier: Topic :: Scientific/Engineering
Classifier: Topic :: Software Development :: Embedded Systems
Classifier: Topic :: Software Development :: Libraries :: Python Modules
Classifier: Topic :: Utilities
